quickd/__init__.py
quickd/factory.py
quickd/inject.py
quickd/service.py
quickd/singletons.py
quickd-0.1.1.dist-info/LICENSE
quickd-0.1.1.dist-info/METADATA
quickd-0.1.1.dist-info/WHEEL
quickd-0.1.1.dist-info/top_level.txt
quickd-0.1.1.dist-info/RECORD
