Metadata-Version: 2.1
Name: quickd
Version: 0.1.1
Summary: Decorator type based dependency injection
Home-page: https://github.com/vimtor/quickd
Author: Victor Navarro
Author-email: victor@vimtor.io
License: MIT
Project-URL: Bug Tracker, https://github.com/vimtor/quickd/issues
Keywords: dependency injection,unif of work,decorators,typings
Platform: UNKNOWN
Classifier: Development Status :: 4 - Beta
Classifier: Intended Audience :: Developers
Classifier: Operating System :: MacOS :: MacOS X
Classifier: Operating System :: Microsoft :: Windows
Classifier: Operating System :: POSIX
Classifier: Topic :: Software Development :: Build Tools
Classifier: Topic :: Software Development :: Testing
Classifier: License :: OSI Approved :: MIT License
Classifier: Programming Language :: Python
Classifier: Programming Language :: Python :: 3.5
Classifier: Programming Language :: Python :: 3.6
Classifier: Programming Language :: Python :: 3.7
Classifier: Programming Language :: Python :: 3.8
Classifier: Programming Language :: Python :: 3.9
Requires-Python: >=3.5
Provides-Extra: build
Requires-Dist: twine ; extra == 'build'
Requires-Dist: wheel ; extra == 'build'
Provides-Extra: tests
Requires-Dist: pytest ; extra == 'tests'
